{
	"format_version": "1.9.0",
	"credit": "Made with Blockbench",
	"parent": "minecraft:block/orientable",
	"textures": {
		"0": "minecraft:block/iron_block",
		"1": "overly_complicated_garbage:block/biomass_processor_lit",
		"particle": "minecraft:block/iron_block"
	},
	"elements": [
		{
			"from": [0, 0, 0],
			"to": [16, 16, 16],
			"faces": {
				"north": {"uv": [0, 0, 16, 16], "texture": "#1"},
				"east": {"uv": [0, 0, 16, 16], "texture": "#0"},
				"south": {"uv": [0, 0, 16, 16], "texture": "#0"},
				"west": {"uv": [0, 0, 16, 16], "texture": "#0"},
				"up": {"uv": [0, 0, 16, 16], "texture": "#0"},
				"down": {"uv": [0, 0, 16, 16], "texture": "#0"}
			}
		}
	]
}